dootle/__init__.py
dootle/index.rst
dootle/__docs/conf.py
dootle/__docs/faq.rst
dootle/__docs/getting_started.rst
dootle/__docs/_static/custom.css
dootle/__docs/_templates/genindex.html
dootle/__docs/_templates/layout.html
dootle/__docs/_templates/autoapi/python/attribute.rst
dootle/__docs/_templates/autoapi/python/class.rst
dootle/__docs/_templates/autoapi/python/data.rst
dootle/__docs/_templates/autoapi/python/debug_obj.rst.jinja
dootle/__docs/_templates/autoapi/python/exception.rst
dootle/__docs/_templates/autoapi/python/function.rst
dootle/__docs/_templates/autoapi/python/method.rst
dootle/__docs/_templates/autoapi/python/module.rst
dootle/__docs/_templates/autoapi/python/package.rst
dootle/__docs/_templates/autoapi/python/property.rst
dootle/__docs/_templates/autoapi/python/utils.jinja
dootle/__docs/_templates/autoapi/python/vis_attrs.rst.jinja
dootle/__docs/_templates/autoapi/python/vis_classes.rst.jinja
dootle/__docs/_templates/autoapi/python/vis_enums.rst.jinja
dootle/__docs/_templates/autoapi/python/vis_excs.rst.jinja
dootle/__docs/_templates/autoapi/python/vis_funcs.rst.jinja
dootle/__docs/_templates/autoapi/python/vis_protos.rst.jinja
dootle/__docs/_templates/autoapi/python/vis_submods.rst.jinja
dootle/__docs/_templates/autoapi/python/vis_types.rst.jinja
dootle/__docs/_templates/autosummary/base.rst
dootle/__docs/_templates/autosummary/class.rst
dootle/__docs/_templates/autosummary/module.rst
dootle/__docs/architecture/overview.rst
dootle/__docs/examples/overview.rst
dootle/__templates/spider_toml
dootle/__templates/epub/epub_css
dootle/__templates/epub/epub_manifest
dootle/__templates/epub/epub_manifest_entry
dootle/__templates/epub/epub_nav
dootle/__templates/epub/epub_nav_entry
dootle/__templates/epub/epub_page_styles
dootle/__templates/epub/epub_spine_entry
dootle/__templates/epub/epub_titlepage
dootle/__templates/jekyll/jekyll_config
dootle/__templates/jekyll/jekyll_post
dootle/__templates/jekyll/jekyll_tag_index
dootle-0.3.2.dist-info/licenses/LICENSE
dootle-0.3.2.dist-info/METADATA
dootle-0.3.2.dist-info/WHEEL
dootle-0.3.2.dist-info/entry_points.txt
dootle-0.3.2.dist-info/top_level.txt
dootle-0.3.2.dist-info/RECORD
